mastodon_fetcher_haystack/__about__.py
mastodon_fetcher_haystack/__init__.py
mastodon_fetcher_haystack/mastodon_fetcher.py
mastodon_fetcher_haystack-0.1.0.dist-info/METADATA
mastodon_fetcher_haystack-0.1.0.dist-info/WHEEL
mastodon_fetcher_haystack-0.1.0.dist-info/licenses/LICENSE.txt
mastodon_fetcher_haystack-0.1.0.dist-info/RECORD
