Metadata-Version: 2.1
Name: mastodon-fetcher-haystack
Version: 0.1.0
Project-URL: Documentation, https://github.com/unknown/mastodon-fetcher-haystack#readme
Project-URL: Issues, https://github.com/unknown/mastodon-fetcher-haystack/issues
Project-URL: Source, https://github.com/unknown/mastodon-fetcher-haystack
Author-email: Tuana Celik <tuana.celik@deepset.ai>
License-Expression: MIT
License-File: LICENSE.txt
Classifier: Development Status :: 4 - Beta
Classifier: Programming Language :: Python
Classifier: Programming Language :: Python :: 3.7
Classifier: Programming Language :: Python :: 3.8
Classifier: Programming Language :: Python :: 3.9
Classifier: Programming Language :: Python :: 3.10
Classifier: Programming Language :: Python :: 3.11
Classifier: Programming Language :: Python :: Implementation :: CPython
Classifier: Programming Language :: Python :: Implementation :: PyPy
Requires-Python: >=3.7
Requires-Dist: haystack-ai
Requires-Dist: html2text
